a_selenium_screenshot_whole_page/LICENSE
a_selenium_screenshot_whole_page/README.MD
a_selenium_screenshot_whole_page/__init__.py
a_selenium_screenshot_whole_page/requirements.txt
a_selenium_screenshot_whole_page/thirdparty.json
a_selenium_screenshot_whole_page-0.10.dist-info/LICENSE.rst
a_selenium_screenshot_whole_page-0.10.dist-info/METADATA
a_selenium_screenshot_whole_page-0.10.dist-info/WHEEL
a_selenium_screenshot_whole_page-0.10.dist-info/top_level.txt
a_selenium_screenshot_whole_page-0.10.dist-info/RECORD
